resfmt/__init__.py
resfmt/__main__.py
resfmt-0.2.0.dist-info/LICENSE
resfmt-0.2.0.dist-info/METADATA
resfmt-0.2.0.dist-info/WHEEL
resfmt-0.2.0.dist-info/entry_points.txt
resfmt-0.2.0.dist-info/top_level.txt
resfmt-0.2.0.dist-info/RECORD
